LICENSE
MANIFEST.in
README.rst
setup.cfg
setup.py
sqla_taskq/__init__.py
sqla_taskq/command.py
sqla_taskq/models.py
sqla_taskq/run_daemon.py
sqla_taskq/run_supervisor.py
sqla_taskq.egg-info/PKG-INFO
sqla_taskq.egg-info/SOURCES.txt
sqla_taskq.egg-info/dependency_links.txt
sqla_taskq.egg-info/entry_points.txt
sqla_taskq.egg-info/not-zip-safe
sqla_taskq.egg-info/requires.txt
sqla_taskq.egg-info/top_level.txt
sqla_taskq/examples/__init__.py
sqla_taskq/examples/add_tasks.py
sqla_taskq/examples/funcs.py
sqla_taskq/scripts/__init__.py
sqla_taskq/scripts/initializedb.py