Metadata-Version: 1.1
Name: sqla-taskq
Version: 0.1
Summary: Simple task queue executed by a daemon
Home-page: UNKNOWN
Author: Aurélien Matouillot
Author-email: a.matouillot@gmail.com
License: MIT
Keywords: taskq,unix,sqlalchemy,task,queue
Platform: UNKNOWN
Classifier: Operating System :: OS Independent
Classifier: Programming Language :: Python
Classifier: Programming Language :: Python :: 2.6
Classifier: Programming Language :: Python :: 2.7
Classifier: Intended Audience :: Developers
Classifier: License :: OSI Approved :: MIT License
